algorithms/__init__.py
algorithms/advanced.py
algorithms/error_correction.py
core/__init__.py
core/circuit.py
core/executor.py
core/gates.py
core/statevector.py
ml/__init__.py
noise/__init__.py
noise/channels.py
optimization/__init__.py
viz/__init__.py
viz/advanced.py
viz/ascii.py
quantumsim_edu-2.0.3.dist-info/METADATA
quantumsim_edu-2.0.3.dist-info/WHEEL
quantumsim_edu-2.0.3.dist-info/entry_points.txt
quantumsim_edu-2.0.3.dist-info/top_level.txt
quantumsim_edu-2.0.3.dist-info/RECORD
