Metadata-Version: 2.4
Name: quantumsim-edu
Version: 2.0.3
Summary: Educational quantum computing simulator for learning and experimentation
Home-page: https://github.com/Vaiditya2207/quantum-projects
Author: Vaiditya Tanwar
Author-email: vaidityatanwar2207@gmail.com
Project-URL: Bug Reports, https://github.com/Vaiditya2207/quantum-projects/issues
Project-URL: Source, https://github.com/Vaiditya2207/quantum-projects
Project-URL: Documentation, https://github.com/Vaiditya2207/quantum-projects/blob/main/README.md
Classifier: Development Status :: 4 - Beta
Classifier: Intended Audience :: Education
Classifier: Intended Audience :: Science/Research
Classifier: License :: OSI Approved :: MIT License
Classifier: Operating System :: OS Independent
Classifier: Programming Language :: Python :: 3
Classifier: Programming Language :: Python :: 3.8
Classifier: Programming Language :: Python :: 3.9
Classifier: Programming Language :: Python :: 3.10
Classifier: Programming Language :: Python :: 3.11
Classifier: Topic :: Scientific/Engineering :: Physics
Classifier: Topic :: Education
Requires-Python: >=3.8
Requires-Dist: numpy>=1.21.0
Requires-Dist: matplotlib>=3.5.0
Provides-Extra: dev
Requires-Dist: pytest>=6.0; extra == "dev"
Requires-Dist: black; extra == "dev"
Requires-Dist: isort; extra == "dev"
Requires-Dist: mypy; extra == "dev"
Provides-Extra: jupyter
Requires-Dist: jupyterlab>=3.0; extra == "jupyter"
Requires-Dist: ipywidgets>=7.0; extra == "jupyter"
Dynamic: author
Dynamic: author-email
Dynamic: classifier
Dynamic: description
Dynamic: description-content-type
Dynamic: home-page
Dynamic: project-url
Dynamic: provides-extra
Dynamic: requires-dist
Dynamic: requires-python
Dynamic: summary
